climate/__init__.py
climate-0.1.0.dist-info/WHEEL
climate-0.1.0.dist-info/METADATA
climate-0.1.0.dist-info/RECORD
