Metadata-Version: 2.1
Name: climate
Version: 0.1.0
Summary: Command line arguments parsing
License: Apache-2.0
Author: Oliver Berger
Author-email: oliver@digitalarchitekt.de
Requires-Python: >=3.7,<4.0
Classifier: License :: OSI Approved :: Apache Software License
Classifier: Programming Language :: Python :: 3
Classifier: Programming Language :: Python :: 3.7
